hydra_profiler/__init__.py
hydra_profiler/profiler.py
hydra_profiler-0.0.1.dist-info/METADATA
hydra_profiler-0.0.1.dist-info/WHEEL
hydra_profiler-0.0.1.dist-info/top_level.txt
hydra_profiler-0.0.1.dist-info/RECORD
